{
  "0x0000": {
    "set1": "@",
    "set2": "0x00",
    "asc1": "@",
    "asc2": "",
    "poke": 0,
    "f1": "C64 Pro",
    "f2": "0x0040"
  },
  "0x0001": {
    "set1": "A",
    "set2": "a",
    "asc1": "A",
    "asc2": "a",
    "poke": 1,
    "f1": "C64 Pro",
    "f2": "0x0041"
  },
  "0x0002": {
    "set1": "B",
    "set2": "b",
    "asc1": "B",
    "asc2": "b",
    "poke": 2,
    "f1": "C64 Pro",
    "f2": "0x0042"
  },
  "0x0003": {
    "set1": "C",
    "set2": "c",
    "asc1": "C",
    "asc2": "c",
    "poke": 3,
    "f1": "C64 Pro",
    "f2": "0x0043"
  },
  "0x0004": {
    "set1": "D",
    "set2": "d",
    "asc1": "D",
    "asc2": "d",
    "poke": 4,
    "f1": "C64 Pro",
    "f2": "0x0044"
  },
  "0x0005": {
    "set1": "E",
    "set2": "e",
    "asc1": "E",
    "asc2": "e",
    "poke": 5,
    "f1": "C64 Pro",
    "f2": "0x0045"
  },
  "0x0006": {
    "set1": "F",
    "set2": "f",
    "asc1": "F",
    "asc2": "f",
    "poke": 6,
    "f1": "C64 Pro",
    "f2": "0x0046"
  },
  "0x0007": {
    "set1": "G",
    "set2": "g",
    "asc1": "G",
    "asc2": "g",
    "poke": 7,
    "f1": "C64 Pro",
    "f2": "0x0047"
  },
  "0x0008": {
    "set1": "H",
    "set2": "h",
    "asc1": "H",
    "asc2": "h",
    "poke": 8,
    "f1": "C64 Pro",
    "f2": "0x0048"
  },
  "0x0009": {
    "set1": "I",
    "set2": "i",
    "asc1": "I",
    "asc2": "i",
    "poke": 9,
    "f1": "C64 Pro",
    "f2": "0x0049"
  },
  "0x000A": {
    "set1": "J",
    "set2": "j",
    "asc1": "J",
    "asc2": "j",
    "poke": 10,
    "f1": "C64 Pro",
    "f2": "0x004A"
  },
  "0x000B": {
    "set1": "K",
    "set2": "k",
    "asc1": "K",
    "asc2": "k",
    "poke": 11,
    "f1": "C64 Pro",
    "f2": "0x004B"
  },
  "0x000C": {
    "set1": "L",
    "set2": "l",
    "asc1": "L",
    "asc2": "l",
    "poke": 12,
    "f1": "C64 Pro",
    "f2": "0x004C"
  },
  "0x000D": {
    "set1": "M",
    "set2": "m",
    "asc1": "M",
    "asc2": "m",
    "poke": 13,
    "f1": "C64 Pro",
    "f2": "0x004D"
  },
  "0x000E": {
    "set1": "N",
    "set2": "n",
    "asc1": "N",
    "asc2": "n",
    "poke": 14,
    "f1": "C64 Pro",
    "f2": "0x004E"
  },
  "0x000F": {
    "set1": "O",
    "set2": "o",
    "asc1": "O",
    "asc2": "o",
    "poke": 15,
    "f1": "C64 Pro",
    "f2": "0x004F"
  },
  "0x0010": {
    "set1": "P",
    "set2": "p",
    "asc1": "P",
    "asc2": "p",
    "poke": 16,
    "f1": "C64 Pro",
    "f2": "0x0050"
  },
  "0x0011": {
    "set1": "Q",
    "set2": "q",
    "asc1": "Q",
    "asc2": "q",
    "poke": 17,
    "f1": "C64 Pro",
    "f2": "0x0051"
  },
  "0x0012": {
    "set1": "R",
    "set2": "r",
    "asc1": "R",
    "asc2": "r",
    "poke": 18,
    "f1": "C64 Pro",
    "f2": "0x0052"
  },
  "0x0013": {
    "set1": "S",
    "set2": "s",
    "asc1": "S",
    "asc2": "s",
    "poke": 19,
    "f1": "C64 Pro",
    "f2": "0x0053"
  },
  "0x0014": {
    "set1": "T",
    "set2": "t",
    "asc1": "T",
    "asc2": "t",
    "poke": 20,
    "f1": "C64 Pro",
    "f2": "0x0054"
  },
  "0x0015": {
    "set1": "U",
    "set2": "u",
    "asc1": "U",
    "asc2": "u",
    "poke": 21,
    "f1": "C64 Pro",
    "f2": "0x0055"
  },
  "0x0016": {
    "set1": "V",
    "set2": "v",
    "asc1": "V",
    "asc2": "v",
    "poke": 22,
    "f1": "C64 Pro",
    "f2": "0x0056"
  },
  "0x0017": {
    "set1": "W",
    "set2": "w",
    "asc1": "W",
    "asc2": "w",
    "poke": 23,
    "f1": "C64 Pro",
    "f2": "0x0057"
  },
  "0x0018": {
    "set1": "X",
    "set2": "x",
    "asc1": "X",
    "asc2": "x",
    "poke": 24,
    "f1": "C64 Pro",
    "f2": "0x0058"
  },
  "0x0019": {
    "set1": "Y",
    "set2": "y",
    "asc1": "Y",
    "asc2": "y",
    "poke": 25,
    "f1": "C64 Pro",
    "f2": "0x0059"
  },
  "0x001A": {
    "set1": "Z",
    "set2": "z",
    "asc1": "Z",
    "asc2": "z",
    "poke": 26,
    "f1": "C64 Pro",
    "f2": "0x005A"
  },
  "0x001B": {
    "set1": "[",
    "set2": "",
    "asc1": "",
    "asc2": "",
    "poke": 27,
    "f1": "C64 Pro",
    "f2": "0xE05B"
  },
  "0x001C": {
    "set1": "L",
    "set2": "",
    "asc1": "",
    "asc2": "",
    "poke": 28,
    "f1": "C64 Pro",
    "f2": "0xE05C"
  },
  "0x001D": {
    "set1": "]",
    "set2": "",
    "asc1": "",
    "asc2": "",
    "poke": 29,
    "f1": "C64 Pro",
    "f2": "0xE05D"
  },
  "0x001E": {
    "set1": "|",
    "set2": "",
    "asc1": "",
    "asc2": "",
    "poke": 30,
    "f1": "C64 Pro",
    "f2": "0x2190"
  },
  "0x001F": {
    "set1": "-",
    "set2": "",
    "asc1": "",
    "asc2": "",
    "poke": 31,
    "f1": "C64 Pro",
    "f2": "0x2191"
  },
  "0x0020": {
    "set1": " ",
    "set2": "",
    "asc1": " ",
    "asc2": "",
    "poke": 32,
    "f1": "C64 Pro",
    "f2": "0x2002"
  },
  "0x0021": {
    "set1": "!",
    "set2": "",
    "asc1": "!",
    "asc2": "",
    "poke": 33,
    "f1": "C64 Pro",
    "f2": "0x0021"
  },
  "0x0022": {
    "set1": "\"",
    "set2": "",
    "asc1": "",
    "asc2": "",
    "poke": 34,
    "f1": "C64 Pro",
    "f2": "0x005C"
  },
  "0x0023": {
    "set1": "#",
    "set2": "",
    "asc1": "",
    "asc2": "",
    "poke": 35,
    "f1": "C64 Pro",
    "f2": "0x0023"
  },
  "0x0024": {
    "set1": "$",
    "set2": "",
    "asc1": "",
    "asc2": "",
    "poke": 36,
    "f1": "C64 Pro",
    "f2": "0x0024"
  },
  "0x0025": {
    "set1": "%",
    "set2": "",
    "asc1": "",
    "asc2": "",
    "poke": 37,
    "f1": "C64 Pro",
    "f2": "0x0025"
  },
  "0x0026": {
    "set1": "&",
    "set2": "",
    "asc1": "",
    "asc2": "",
    "poke": 38,
    "f1": "C64 Pro",
    "f2": "0x0026"
  },
  "0x0027": {
    "set1": "´",
    "set2": "",
    "asc1": "",
    "asc2": "",
    "poke": 39,
    "f1": "C64 Pro",
    "f2": "0x0027"
  },
  "0x0028": {
    "set1": "(",
    "set2": "",
    "asc1": "",
    "asc2": "",
    "poke": 40,
    "f1": "C64 Pro",
    "f2": "0x0028"
  },
  "0x0029": {
    "set1": ")",
    "set2": "",
    "asc1": "",
    "asc2": "",
    "poke": 41,
    "f1": "C64 Pro",
    "f2": "0x0029"
  },
  "0x002A": {
    "set1": "*",
    "set2": "",
    "asc1": "",
    "asc2": "",
    "poke": 42,
    "f1": "C64 Pro",
    "f2": "0x002A"
  },
  "0x002B": {
    "set1": "+",
    "set2": "",
    "asc1": "",
    "asc2": "",
    "poke": 43,
    "f1": "C64 Pro",
    "f2": "0x002B"
  },
  "0x002C": {
    "set1": ",",
    "set2": "",
    "asc1": "",
    "asc2": "",
    "poke": 44,
    "f1": "C64 Pro",
    "f2": "0x002C"
  },
  "0x002D": {
    "set1": "-",
    "set2": "",
    "asc1": "",
    "asc2": "",
    "poke": 45,
    "f1": "C64 Pro",
    "f2": "0x002D"
  },
  "0x002E": {
    "set1": ".",
    "set2": "",
    "asc1": "",
    "asc2": "",
    "poke": 46,
    "f1": "C64 Pro",
    "f2": "0x002E"
  },
  "0x002F": {
    "set1": "/",
    "set2": "",
    "asc1": "",
    "asc2": "",
    "poke": 47,
    "f1": "C64 Pro",
    "f2": "0x002F"
  },
  "0x0030": {
    "set1": "0",
    "set2": "",
    "asc1": "",
    "asc2": "",
    "poke": 48,
    "f1": "C64 Pro",
    "f2": "0x0030"
  },
  "0x0031": {
    "set1": "1",
    "set2": "",
    "asc1": "",
    "asc2": "",
    "poke": 49,
    "f1": "C64 Pro",
    "f2": "0x0031"
  },
  "0x0032": {
    "set1": "2",
    "set2": "",
    "asc1": "",
    "asc2": "",
    "poke": 50,
    "f1": "C64 Pro",
    "f2": "0x0032"
  },
  "0x0033": {
    "set1": "3",
    "set2": "",
    "asc1": "",
    "asc2": "",
    "poke": 51,
    "f1": "C64 Pro",
    "f2": "0x0033"
  },
  "0x0034": {
    "set1": "4",
    "set2": "",
    "asc1": "",
    "asc2": "",
    "poke": 52,
    "f1": "C64 Pro",
    "f2": "0x0034"
  },
  "0x0035": {
    "set1": "5",
    "set2": "",
    "asc1": "",
    "asc2": "",
    "poke": 53,
    "f1": "C64 Pro",
    "f2": "0x0035"
  },
  "0x0036": {
    "set1": "6",
    "set2": "",
    "asc1": "",
    "asc2": "",
    "poke": 54,
    "f1": "C64 Pro",
    "f2": "0x0036"
  },
  "0x0037": {
    "set1": "7",
    "set2": "",
    "asc1": "",
    "asc2": "",
    "poke": 55,
    "f1": "C64 Pro",
    "f2": "0x0037"
  },
  "0x0038": {
    "set1": "8",
    "set2": "",
    "asc1": "",
    "asc2": "",
    "poke": 56,
    "f1": "C64 Pro",
    "f2": "0x0038"
  },
  "0x0039": {
    "set1": "9",
    "set2": "",
    "asc1": "",
    "asc2": "",
    "poke": 57,
    "f1": "C64 Pro",
    "f2": "0x0039"
  },
  "0x003C": {
    "set1": ":",
    "set2": "",
    "asc1": "",
    "asc2": "",
    "poke": 58,
    "f1": "C64 Pro",
    "f2": "0x003A"
  },
  "0x003D": {
    "set1": ";",
    "set2": "",
    "asc1": "",
    "asc2": "",
    "poke": 59,
    "f1": "C64 Pro",
    "f2": "0x003B"
  },
  "0x003E": {
    "set1": "<",
    "set2": "",
    "asc1": "",
    "asc2": "",
    "poke": 60,
    "f1": "C64 Pro",
    "f2": "0x003C"
  },
  "0x003F": {
    "set1": "=",
    "set2": "",
    "asc1": "",
    "asc2": "",
    "poke": 61,
    "f1": "C64 Pro",
    "f2": "0x003D"
  },
  "0x0040": {
    "set1": ">",
    "set2": "",
    "asc1": "",
    "asc2": "",
    "poke": 62,
    "f1": "C64 Pro",
    "f2": "0x003E"
  },
  "0x0041": {
    "set1": "?",
    "set2": "",
    "asc1": "",
    "asc2": "",
    "poke": 63,
    "f1": "C64 Pro",
    "f2": "0x003F"
  },
  "0x0042": {
    "set1": "0xE0D2",
    "set2": "",
    "asc1": "",
    "asc2": "",
    "poke": 64,
    "f1": "C64 Pro",
    "f2": "0x0040"
  },
  "0x0043": {
    "set1": "0x2660",
    "set2": "A",
    "asc1": "",
    "asc2": "",
    "poke": 65,
    "f1": "C64 Pro",
    "f2": "0x0041"
  },
  "0x0044": {
    "set1": "0x2502",
    "set2": "B",
    "asc1": "",
    "asc2": "",
    "poke": 66,
    "f1": "C64 Pro",
    "f2": "0x2502"
  },
  "0x0045": {
    "set1": "0x2560",
    "set2": "C",
    "asc1": "",
    "asc2": "",
    "poke": 67,
    "f1": "C64 Pro",
    "f2": "0x2560"
  },
  "0x0046": {
    "set1": "0x0",
    "set2": "D",
    "asc1": "",
    "asc2": "",
    "poke": 68,
    "f1": "C64 Pro",
    "f2": "0x0000"
  },
  "0x0047": {
    "set1": "0x0",
    "set2": "E",
    "asc1": "",
    "asc2": "",
    "poke": 69,
    "f1": "C64 Pro",
    "f2": "0x0000"
  },
  "0x0048": {
    "set1": "0x0",
    "set2": "F",
    "asc1": "",
    "asc2": "",
    "poke": 70,
    "f1": "C64 Pro",
    "f2": "0x0000"
  },
  "0x0049": {
    "set1": "0x0",
    "set2": "G",
    "asc1": "",
    "asc2": "",
    "poke": 71,
    "f1": "C64 Pro",
    "f2": "0x0000"
  },
  "0x004A": {
    "set1": "0x0",
    "set2": "H",
    "asc1": "",
    "asc2": "",
    "poke": 72,
    "f1": "C64 Pro",
    "f2": "0x0000"
  },
  "0x004B": {
    "set1": "0x0",
    "set2": "I",
    "asc1": "",
    "asc2": "",
    "poke": 73,
    "f1": "C64 Pro",
    "f2": "0x0000"
  },
  "0x004C": {
    "set1": "0x0",
    "set2": "J",
    "asc1": "",
    "asc2": "",
    "poke": 74,
    "f1": "C64 Pro",
    "f2": "0x0000"
  },
  "0x004D": {
    "set1": "0x0",
    "set2": "K",
    "asc1": "",
    "asc2": "",
    "poke": 75,
    "f1": "C64 Pro",
    "f2": "0x0000"
  },
  "0x004E": {
    "set1": "0x0",
    "set2": "L",
    "asc1": "",
    "asc2": "",
    "poke": 76,
    "f1": "C64 Pro",
    "f2": "0x0000"
  },
  "0x004F": {
    "set1": "0x0",
    "set2": "M",
    "asc1": "",
    "asc2": "",
    "poke": 77,
    "f1": "C64 Pro",
    "f2": "0x0000"
  },
  "0x0050": {
    "set1": "0x0",
    "set2": "N",
    "asc1": "",
    "asc2": "",
    "poke": 78,
    "f1": "C64 Pro",
    "f2": "0x0000"
  },
  "0x0051": {
    "set1": "0x0",
    "set2": "O",
    "asc1": "",
    "asc2": "",
    "poke": 79,
    "f1": "C64 Pro",
    "f2": "0x0000"
  },
  "0x0052": {
    "set1": "0x0",
    "set2": "P",
    "asc1": "",
    "asc2": "",
    "poke": 80,
    "f1": "C64 Pro",
    "f2": "0x0000"
  },
  "0x0053": {
    "set1": "0x0",
    "set2": "Q",
    "asc1": "",
    "asc2": "",
    "poke": 81,
    "f1": "C64 Pro",
    "f2": "0x0000"
  },
  "0x0054": {
    "set1": "0x0",
    "set2": "R",
    "asc1": "",
    "asc2": "",
    "poke": 82,
    "f1": "C64 Pro",
    "f2": "0x0000"
  },
  "0x0055": {
    "set1": "0x0",
    "set2": "S",
    "asc1": "",
    "asc2": "",
    "poke": 83,
    "f1": "C64 Pro",
    "f2": "0x0000"
  },
  "0x0056": {
    "set1": "0x0",
    "set2": "T",
    "asc1": "",
    "asc2": "",
    "poke": 84,
    "f1": "C64 Pro",
    "f2": "0x0000"
  },
  "0x0057": {
    "set1": "0x0",
    "set2": "U",
    "asc1": "",
    "asc2": "",
    "poke": 85,
    "f1": "C64 Pro",
    "f2": "0x0000"
  },
  "0x0058": {
    "set1": "0x0",
    "set2": "V",
    "asc1": "",
    "asc2": "",
    "poke": 86,
    "f1": "C64 Pro",
    "f2": "0x0000"
  },
  "0x0059": {
    "set1": "0x0",
    "set2": "W",
    "asc1": "",
    "asc2": "",
    "poke": 87,
    "f1": "C64 Pro",
    "f2": "0x0000"
  },
  "0x005A": {
    "set1": "0x0",
    "set2": "X",
    "asc1": "",
    "asc2": "",
    "poke": 88,
    "f1": "C64 Pro",
    "f2": "0x0000"
  },
  "0x005B": {
    "set1": "0x0",
    "set2": "Y",
    "asc1": "",
    "asc2": "",
    "poke": 89,
    "f1": "C64 Pro",
    "f2": "0x0000"
  },
  "0x005C": {
    "set1": "0x0",
    "set2": "Z",
    "asc1": "",
    "asc2": "",
    "poke": 90,
    "f1": "C64 Pro",
    "f2": "0x0000"
  },
  "0x005D": {
    "set1": "?",
    "set2": "",
    "asc1": "",
    "asc2": "",
    "poke": 91,
    "f1": "C64 Pro",
    "f2": "0x003F"
  },
  "0x005E": {
    "set1": "?",
    "set2": "",
    "asc1": "",
    "asc2": "",
    "poke": 92,
    "f1": "C64 Pro",
    "f2": "0x003F"
  },
  "0x005F": {
    "set1": "?",
    "set2": "",
    "asc1": "",
    "asc2": "",
    "poke": 93,
    "f1": "C64 Pro",
    "f2": "0x003F"
  },
  "0x0060": {
    "set1": "?",
    "set2": "",
    "asc1": "",
    "asc2": "",
    "poke": 94,
    "f1": "C64 Pro",
    "f2": "0x003F"
  },
  "0x0061": {
    "set1": "?",
    "set2": "",
    "asc1": "",
    "asc2": "",
    "poke": 95,
    "f1": "C64 Pro",
    "f2": "0x003F"
  },
  "0x0062": {
    "set1": "?",
    "set2": "",
    "asc1": "",
    "asc2": "",
    "poke": 96,
    "f1": "C64 Pro",
    "f2": "0x003F"
  },
  "0x0063": {
    "set1": "?",
    "set2": "",
    "asc1": "",
    "asc2": "",
    "poke": 97,
    "f1": "C64 Pro",
    "f2": "0x003F"
  },
  "0x0064": {
    "set1": "?",
    "set2": "",
    "asc1": "",
    "asc2": "",
    "poke": 98,
    "f1": "C64 Pro",
    "f2": "0x003F"
  },
  "0x0065": {
    "set1": "?",
    "set2": "",
    "asc1": "",
    "asc2": "",
    "poke": 99,
    "f1": "C64 Pro",
    "f2": "0x003F"
  },
  "0x0066": {
    "set1": "?",
    "set2": "",
    "asc1": "",
    "asc2": "",
    "poke": 100,
    "f1": "C64 Pro",
    "f2": "0x003F"
  },
  "0x0067": {
    "set1": "?",
    "set2": "",
    "asc1": "",
    "asc2": "",
    "poke": 101,
    "f1": "C64 Pro",
    "f2": "0x003F"
  },
  "0x0068": {
    "set1": "?",
    "set2": "",
    "asc1": "",
    "asc2": "",
    "poke": 102,
    "f1": "C64 Pro",
    "f2": "0x003F"
  },
  "0x0069": {
    "set1": "?",
    "set2": "",
    "asc1": "",
    "asc2": "",
    "poke": 103,
    "f1": "C64 Pro",
    "f2": "0x003F"
  },
  "0x006A": {
    "set1": "?",
    "set2": "",
    "asc1": "",
    "asc2": "",
    "poke": 104,
    "f1": "C64 Pro",
    "f2": "0x003F"
  },
  "0x006B": {
    "set1": "?",
    "set2": "",
    "asc1": "",
    "asc2": "",
    "poke": 105,
    "f1": "C64 Pro",
    "f2": "0x003F"
  },
  "0x006C": {
    "set1": "?",
    "set2": "",
    "asc1": "",
    "asc2": "",
    "poke": 106,
    "f1": "C64 Pro",
    "f2": "0x003F"
  },
  "0x006D": {
    "set1": "?",
    "set2": "",
    "asc1": "",
    "asc2": "",
    "poke": 107,
    "f1": "C64 Pro",
    "f2": "0x003F"
  },
  "0x006E": {
    "set1": "?",
    "set2": "",
    "asc1": "",
    "asc2": "",
    "poke": 108,
    "f1": "C64 Pro",
    "f2": "0x003F"
  },
  "0x006F": {
    "set1": "?",
    "set2": "",
    "asc1": "",
    "asc2": "",
    "poke": 109,
    "f1": "C64 Pro",
    "f2": "0x003F"
  },
  "0x0070": {
    "set1": "?",
    "set2": "",
    "asc1": "",
    "asc2": "",
    "poke": 110,
    "f1": "C64 Pro",
    "f2": "0x003F"
  },
  "0x0071": {
    "set1": "?",
    "set2": "",
    "asc1": "",
    "asc2": "",
    "poke": 111,
    "f1": "C64 Pro",
    "f2": "0x003F"
  },
  "0x0072": {
    "set1": "?",
    "set2": "",
    "asc1": "",
    "asc2": "",
    "poke": 112,
    "f1": "C64 Pro",
    "f2": "0x003F"
  },
  "0x0073": {
    "set1": "?",
    "set2": "",
    "asc1": "",
    "asc2": "",
    "poke": 113,
    "f1": "C64 Pro",
    "f2": "0x003F"
  },
  "0x0074": {
    "set1": "?",
    "set2": "",
    "asc1": "",
    "asc2": "",
    "poke": 114,
    "f1": "C64 Pro",
    "f2": "0x003F"
  },
  "0x0075": {
    "set1": "?",
    "set2": "",
    "asc1": "",
    "asc2": "",
    "poke": 115,
    "f1": "C64 Pro",
    "f2": "0x003F"
  },
  "0x0076": {
    "set1": "?",
    "set2": "",
    "asc1": "",
    "asc2": "",
    "poke": 116,
    "f1": "C64 Pro",
    "f2": "0x003F"
  },
  "0x0077": {
    "set1": "?",
    "set2": "",
    "asc1": "",
    "asc2": "",
    "poke": 117,
    "f1": "C64 Pro",
    "f2": "0x003F"
  },
  "0x0078": {
    "set1": "?",
    "set2": "",
    "asc1": "",
    "asc2": "",
    "poke": 118,
    "f1": "C64 Pro",
    "f2": "0x003F"
  },
  "0x0079": {
    "set1": "?",
    "set2": "",
    "asc1": "",
    "asc2": "",
    "poke": 119,
    "f1": "C64 Pro",
    "f2": "0x003F"
  },
  "0x007A": {
    "set1": "?",
    "set2": "",
    "asc1": "",
    "asc2": "",
    "poke": 120,
    "f1": "C64 Pro",
    "f2": "0x003F"
  },
  "0x007B": {
    "set1": "?",
    "set2": "",
    "asc1": "",
    "asc2": "",
    "poke": 121,
    "f1": "C64 Pro",
    "f2": "0x003F"
  },
  "0x007C": {
    "set1": "?",
    "set2": "",
    "asc1": "",
    "asc2": "",
    "poke": 122,
    "f1": "C64 Pro",
    "f2": "0x003F"
  },
  "0x007D": {
    "set1": "?",
    "set2": "",
    "asc1": "",
    "asc2": "",
    "poke": 123,
    "f1": "C64 Pro",
    "f2": "0x003F"
  },
  "0x007E": {
    "set1": "?",
    "set2": "",
    "asc1": "",
    "asc2": "",
    "poke": 124,
    "f1": "C64 Pro",
    "f2": "0x003F"
  },
  "0x007F": {
    "set1": "?",
    "set2": "",
    "asc1": "",
    "asc2": "",
    "poke": 125,
    "f1": "C64 Pro",
    "f2": "0x003F"
  },
  "0x0080": {
    "set1": "?",
    "set2": "",
    "asc1": "",
    "asc2": "",
    "poke": 126,
    "f1": "C64 Pro",
    "f2": "0x0000"
  },
  "0x0081": {
    "set1": "?",
    "set2": "",
    "asc1": "",
    "asc2": "",
    "poke": 127,
    "f1": "C64 Pro",
    "f2": "0x0000"
  }
}